RookieTools/CheckBase.py
RookieTools/PasswordCheckBase.py
RookieTools/WebFileCheckBase.py
RookieTools/__init__.py
RookieTools/common.py
RookieTools/ip.py
RookieTools/logger.py
RookieTools/urllib3_hook.py
Test/__init__.py
Test/test_common.py
Test/test_webfile.py
RookieTools-1.15.dist-info/LICENSE
RookieTools-1.15.dist-info/METADATA
RookieTools-1.15.dist-info/WHEEL
RookieTools-1.15.dist-info/top_level.txt
RookieTools-1.15.dist-info/RECORD
