Metadata-Version: 2.1
Name: RookieTools
Version: 1.15
Summary: setup RookieTools
Home-page: https://github.com/hyll8882019/RookieTools
Author: Rookie
Author-email: hyll8882019@outlook.com
License: MIT
Keywords: setup,RookieTools
Platform: any
Requires-Dist: requests
Requires-Dist: lxml
Requires-Dist: chardet
Requires-Dist: tldextract
Requires-Dist: urllib3
Requires-Dist: IPy
